pep487/__init__.py
pep487/version.py
pep487-1.0.1.dist-info/DESCRIPTION.rst
pep487-1.0.1.dist-info/METADATA
pep487-1.0.1.dist-info/RECORD
pep487-1.0.1.dist-info/WHEEL
pep487-1.0.1.dist-info/metadata.json
pep487-1.0.1.dist-info/top_level.txt
