Metadata-Version: 2.0
Name: pep487
Version: 1.0.1
Summary: PEP487 - Simpler customisation of class creation
Home-page: https://github.com/zaehlwerk/pep487
Author: Gregor Giesen
Author-email: giesen@zaehlwerk.net
License: GPLv3
Keywords: pep487
Platform: UNKNOWN
Classifier: Development Status :: 5 - Production/Stable
Classifier: Intended Audience :: Developers
Classifier: License :: OSI Approved :: GNU General Public License v3 or later (GPLv3+)
Classifier: Programming Language :: Python
Classifier: Programming Language :: Python :: 3.4
Classifier: Programming Language :: Python :: 3.5
Classifier: Programming Language :: Python :: 3.6
Provides-Extra: test
Provides-Extra: test
Requires-Dist: pytest; extra == 'test'
Requires-Dist: pytest-cov; extra == 'test'
Requires-Dist: pytest-flakes; extra == 'test'
Requires-Dist: pytest-mock; extra == 'test'
Requires-Dist: pytest-pep8; extra == 'test'
Requires-Dist: pytest-runner; extra == 'test'
